goals_from_team_statistic/__init__.py
goals_from_team_statistic/io.py
goals_from_team_statistic-0.1.0.dist-info/LICENSE
goals_from_team_statistic-0.1.0.dist-info/WHEEL
goals_from_team_statistic-0.1.0.dist-info/METADATA
goals_from_team_statistic-0.1.0.dist-info/RECORD
