Metadata-Version: 2.1
Name: goals_from_team_statistic
Version: 0.1.0
Summary: A template Python module
Home-page: https://github.com/niesfutbol/goals_from_team_statistic
Author: NIES
Author-email: nepo@nies.futbol
Requires-Python: >=3.9
Classifier: License :: OSI Approved :: GNU General Public License v3 or later (GPLv3+)
